{"nodes": [{"id": "a_albdo_v_0_1_0_src_ir_conformance_rs", "label": "conformance.rs", "file_type": "code", "source_file": "src/ir/conformance.rs", "source_location": "L1"}, {"id": "ir_conformance_canonical_v1_frame", "label": "canonical_v1_frame()", "file_type": "code", "source_file": "src/ir/conformance.rs", "source_location": "L59"}, {"id": "opcodeframe", "label": "OpcodeFrame", "file_type": "code", "source_file": "", "source_location": ""}, {"id": "ir_conformance_canonical_v1_frame_round_trips", "label": "canonical_v1_frame_round_trips()", "file_type": "code", "source_file": "src/ir/conformance.rs", "source_location": "L144"}, {"id": "ir_conformance_canonical_v2_frame_covers_every_instruction_variant", "label": "canonical_v2_frame_covers_every_instruction_variant()", "file_type": "code", "source_file": "src/ir/conformance.rs", "source_location": "L154"}], "edges": [{"source": "a_albdo_v_0_1_0_src_ir_conformance_rs", "target": "opcode", "relation": "imports_from", "confidence": "EXTRACTED", "source_file": "src/ir/conformance.rs", "source_location": "L15", "weight": 1.0, "context": "import"}, {"source": "a_albdo_v_0_1_0_src_ir_conformance_rs", "target": "ir_conformance_canonical_v1_frame", "relation": "contains", "confidence": "EXTRACTED", "source_file": "src/ir/conformance.rs", "source_location": "L59", "weight": 1.0}, {"source": "ir_conformance_canonical_v1_frame", "target": "opcodeframe", "relation": "references", "confidence": "EXTRACTED", "source_file": "src/ir/conformance.rs", "source_location": "L59", "weight": 1.0, "context": "return_type"}, {"source": "a_albdo_v_0_1_0_src_ir_conformance_rs", "target": "super", "relation": "imports_from", "confidence": "EXTRACTED", "source_file": "src/ir/conformance.rs", "source_location": "L140", "weight": 1.0, "context": "import"}, {"source": "a_albdo_v_0_1_0_src_ir_conformance_rs", "target": "wire", "relation": "imports_from", "confidence": "EXTRACTED", "source_file": "src/ir/conformance.rs", "source_location": "L141", "weight": 1.0, "context": "import"}, {"source": "a_albdo_v_0_1_0_src_ir_conformance_rs", "target": "ir_conformance_canonical_v1_frame_round_trips", "relation": "contains", "confidence": "EXTRACTED", "source_file": "src/ir/conformance.rs", "source_location": "L144", "weight": 1.0}, {"source": "a_albdo_v_0_1_0_src_ir_conformance_rs", "target": "ir_conformance_canonical_v2_frame_covers_every_instruction_variant", "relation": "contains", "confidence": "EXTRACTED", "source_file": "src/ir/conformance.rs", "source_location": "L154", "weight": 1.0}, {"source": "ir_conformance_canonical_v1_frame_round_trips", "target": "ir_conformance_canonical_v1_frame", "relation": "calls", "context": "call", "confidence": "EXTRACTED", "source_file": "src/ir/conformance.rs", "source_location": "L145", "weight": 1.0}, {"source": "ir_conformance_canonical_v2_frame_covers_every_instruction_variant", "target": "ir_conformance_canonical_v1_frame", "relation": "calls", "context": "call", "confidence": "EXTRACTED", "source_file": "src/ir/conformance.rs", "source_location": "L159", "weight": 1.0}], "raw_calls": [{"caller_nid": "ir_conformance_canonical_v1_frame_round_trips", "callee": "encode_frame", "is_member_call": false, "source_file": "A:\\AlBDO-v-0.1.0\\src\\ir\\conformance.rs", "source_location": "L146"}, {"caller_nid": "ir_conformance_canonical_v1_frame_round_trips", "callee": "decode_frame", "is_member_call": false, "source_file": "A:\\AlBDO-v-0.1.0\\src\\ir\\conformance.rs", "source_location": "L148"}]}