{"nodes": [{"id": "a_albdo_v_0_1_0_using_albedo_md", "label": "USING-ALBEDO.md", "file_type": "document", "source_file": "USING-ALBEDO.md", "source_location": "L1"}, {"id": "albdo_v_0_1_0_using_albedo_using_albdo", "label": "Using AlBDO", "file_type": "document", "source_file": "USING-ALBEDO.md", "source_location": "L1"}, {"id": "albdo_v_0_1_0_using_albedo_1_install_the_binary", "label": "1. Install the binary", "file_type": "document", "source_file": "USING-ALBEDO.md", "source_location": "L6"}, {"id": "albdo_v_0_1_0_using_albedo_2_create_a_project", "label": "2. Create a project", "file_type": "document", "source_file": "USING-ALBEDO.md", "source_location": "L25"}, {"id": "albdo_v_0_1_0_using_albedo_3_three_commands", "label": "3. Three commands", "file_type": "document", "source_file": "USING-ALBEDO.md", "source_location": "L55"}, {"id": "albdo_v_0_1_0_using_albedo_4_authoring_conventions", "label": "4. Authoring conventions", "file_type": "document", "source_file": "USING-ALBEDO.md", "source_location": "L72"}, {"id": "albdo_v_0_1_0_using_albedo_file_based_routing", "label": "File-based routing", "file_type": "document", "source_file": "USING-ALBEDO.md", "source_location": "L74"}, {"id": "albdo_v_0_1_0_using_albedo_layouts", "label": "Layouts", "file_type": "document", "source_file": "USING-ALBEDO.md", "source_location": "L91"}, {"id": "albdo_v_0_1_0_using_albedo_state_actions", "label": "State + actions", "file_type": "document", "source_file": "USING-ALBEDO.md", "source_location": "L111"}, {"id": "albdo_v_0_1_0_using_albedo_css_modules", "label": "CSS modules", "file_type": "document", "source_file": "USING-ALBEDO.md", "source_location": "L151"}, {"id": "albdo_v_0_1_0_using_albedo_tier_budget", "label": "Tier budget", "file_type": "document", "source_file": "USING-ALBEDO.md", "source_location": "L173"}, {"id": "albdo_v_0_1_0_using_albedo_5_deploy", "label": "5. Deploy", "file_type": "document", "source_file": "USING-ALBEDO.md", "source_location": "L190"}, {"id": "albdo_v_0_1_0_using_albedo_6_where_to_look_next", "label": "6. Where to look next", "file_type": "document", "source_file": "USING-ALBEDO.md", "source_location": "L201"}, {"id": "albdo_v_0_1_0_using_albedo_system_setup", "label": "System setup", "file_type": "document", "source_file": "USING-ALBEDO.md", "source_location": "L209"}], "edges": [{"source": "a_albdo_v_0_1_0_using_albedo_md", "target": "albdo_v_0_1_0_using_albedo_using_albdo", "relation": "contains", "confidence": "EXTRACTED", "source_file": "USING-ALBEDO.md", "source_location": "L1", "weight": 1.0}, {"source": "a_albdo_v_0_1_0_using_albedo_md", "target": "a_albdo_v_0_1_0_readme_md", "relation": "references", "confidence": "EXTRACTED", "source_file": "USING-ALBEDO.md", "source_location": "L3", "weight": 1.0}, {"source": "a_albdo_v_0_1_0_using_albedo_md", "target": "a_albdo_v_0_1_0_scaffold_readme_md", "relation": "references", "confidence": "EXTRACTED", "source_file": "USING-ALBEDO.md", "source_location": "L4", "weight": 1.0}, {"source": "albdo_v_0_1_0_using_albedo_using_albdo", "target": "albdo_v_0_1_0_using_albedo_1_install_the_binary", "relation": "contains", "confidence": "EXTRACTED", "source_file": "USING-ALBEDO.md", "source_location": "L6", "weight": 1.0}, {"source": "albdo_v_0_1_0_using_albedo_using_albdo", "target": "albdo_v_0_1_0_using_albedo_2_create_a_project", "relation": "contains", "confidence": "EXTRACTED", "source_file": "USING-ALBEDO.md", "source_location": "L25", "weight": 1.0}, {"source": "albdo_v_0_1_0_using_albedo_using_albdo", "target": "albdo_v_0_1_0_using_albedo_3_three_commands", "relation": "contains", "confidence": "EXTRACTED", "source_file": "USING-ALBEDO.md", "source_location": "L55", "weight": 1.0}, {"source": "albdo_v_0_1_0_using_albedo_using_albdo", "target": "albdo_v_0_1_0_using_albedo_4_authoring_conventions", "relation": "contains", "confidence": "EXTRACTED", "source_file": "USING-ALBEDO.md", "source_location": "L72", "weight": 1.0}, {"source": "albdo_v_0_1_0_using_albedo_4_authoring_conventions", "target": "albdo_v_0_1_0_using_albedo_file_based_routing", "relation": "contains", "confidence": "EXTRACTED", "source_file": "USING-ALBEDO.md", "source_location": "L74", "weight": 1.0}, {"source": "albdo_v_0_1_0_using_albedo_4_authoring_conventions", "target": "albdo_v_0_1_0_using_albedo_layouts", "relation": "contains", "confidence": "EXTRACTED", "source_file": "USING-ALBEDO.md", "source_location": "L91", "weight": 1.0}, {"source": "albdo_v_0_1_0_using_albedo_4_authoring_conventions", "target": "albdo_v_0_1_0_using_albedo_state_actions", "relation": "contains", "confidence": "EXTRACTED", "source_file": "USING-ALBEDO.md", "source_location": "L111", "weight": 1.0}, {"source": "albdo_v_0_1_0_using_albedo_4_authoring_conventions", "target": "albdo_v_0_1_0_using_albedo_css_modules", "relation": "contains", "confidence": "EXTRACTED", "source_file": "USING-ALBEDO.md", "source_location": "L151", "weight": 1.0}, {"source": "albdo_v_0_1_0_using_albedo_4_authoring_conventions", "target": "albdo_v_0_1_0_using_albedo_tier_budget", "relation": "contains", "confidence": "EXTRACTED", "source_file": "USING-ALBEDO.md", "source_location": "L173", "weight": 1.0}, {"source": "albdo_v_0_1_0_using_albedo_using_albdo", "target": "albdo_v_0_1_0_using_albedo_5_deploy", "relation": "contains", "confidence": "EXTRACTED", "source_file": "USING-ALBEDO.md", "source_location": "L190", "weight": 1.0}, {"source": "albdo_v_0_1_0_using_albedo_using_albdo", "target": "albdo_v_0_1_0_using_albedo_6_where_to_look_next", "relation": "contains", "confidence": "EXTRACTED", "source_file": "USING-ALBEDO.md", "source_location": "L201", "weight": 1.0}, {"source": "a_albdo_v_0_1_0_using_albedo_md", "target": "a_albdo_v_0_1_0_benchmarks_parity_readme_md", "relation": "references", "confidence": "EXTRACTED", "source_file": "USING-ALBEDO.md", "source_location": "L204", "weight": 1.0}, {"source": "albdo_v_0_1_0_using_albedo_using_albdo", "target": "albdo_v_0_1_0_using_albedo_system_setup", "relation": "contains", "confidence": "EXTRACTED", "source_file": "USING-ALBEDO.md", "source_location": "L209", "weight": 1.0}], "input_tokens": 0, "output_tokens": 0}