{"nodes": [{"id": "a_albdo_v_0_1_0_src_analysis_topological_rs", "label": "topological.rs", "file_type": "code", "source_file": "src/analysis/topological.rs", "source_location": "L1"}, {"id": "analysis_topological_topologicalsorter", "label": "TopologicalSorter", "file_type": "code", "source_file": "src/analysis/topological.rs", "source_location": "L4"}, {"id": "componentgraph", "label": "ComponentGraph", "file_type": "code", "source_file": "", "source_location": ""}, {"id": "analysis_topological_topologicalsorter_a", "label": "TopologicalSorter<'a>", "file_type": "code", "source_file": "src/analysis/topological.rs", "source_location": "L8"}, {"id": "analysis_topological_topologicalsorter_a_new", "label": ".new()", "file_type": "code", "source_file": "src/analysis/topological.rs", "source_location": "L9"}, {"id": "self", "label": "Self", "file_type": "code", "source_file": "", "source_location": ""}, {"id": "analysis_topological_topologicalsorter_a_sort", "label": ".sort()", "file_type": "code", "source_file": "src/analysis/topological.rs", "source_location": "L12"}, {"id": "result", "label": "Result", "file_type": "code", "source_file": "", "source_location": ""}, {"id": "vec", "label": "Vec", "file_type": "code", "source_file": "", "source_location": ""}, {"id": "componentid", "label": "ComponentId", "file_type": "code", "source_file": "", "source_location": ""}, {"id": "analysis_topological_topologicalsorter_a_sort_with_priority", "label": ".sort_with_priority()", "file_type": "code", "source_file": "src/analysis/topological.rs", "source_location": "L68"}, {"id": "hashmap", "label": "HashMap", "file_type": "code", "source_file": "", "source_location": ""}, {"id": "componentanalysis", "label": "ComponentAnalysis", "file_type": "code", "source_file": "", "source_location": ""}, {"id": "analysis_topological_topologicalsorter_a_create_batches", "label": ".create_batches()", "file_type": "code", "source_file": "src/analysis/topological.rs", "source_location": "L85"}, {"id": "renderbatch", "label": "RenderBatch", "file_type": "code", "source_file": "", "source_location": ""}, {"id": "analysis_topological_find_critical_path", "label": "find_critical_path()", "file_type": "code", "source_file": "src/analysis/topological.rs", "source_location": "L112"}, {"id": "analysis_topological_find_longest_path_from", "label": "find_longest_path_from()", "file_type": "code", "source_file": "src/analysis/topological.rs", "source_location": "L135"}, {"id": "hashset", "label": "HashSet", "file_type": "code", "source_file": "", "source_location": ""}, {"id": "analysis_topological_create_test_graph", "label": "create_test_graph()", "file_type": "code", "source_file": "src/analysis/topological.rs", "source_location": "L178"}, {"id": "analysis_topological_test_topological_sort", "label": "test_topological_sort()", "file_type": "code", "source_file": "src/analysis/topological.rs", "source_location": "L199"}, {"id": "analysis_topological_test_empty_graph", "label": "test_empty_graph()", "file_type": "code", "source_file": "src/analysis/topological.rs", "source_location": "L211"}, {"id": "analysis_topological_test_critical_path", "label": "test_critical_path()", "file_type": "code", "source_file": "src/analysis/topological.rs", "source_location": "L220"}], "edges": [{"source": "a_albdo_v_0_1_0_src_analysis_topological_rs", "target": "componentgraph", "relation": "imports_from", "confidence": "EXTRACTED", "source_file": "src/analysis/topological.rs", "source_location": "L1", "weight": 1.0, "context": "import"}, {"source": "a_albdo_v_0_1_0_src_analysis_topological_rs", "target": "types", "relation": "imports_from", "confidence": "EXTRACTED", "source_file": "src/analysis/topological.rs", "source_location": "L2", "weight": 1.0, "context": "import"}, {"source": "a_albdo_v_0_1_0_src_analysis_topological_rs", "target": "collections", "relation": "imports_from", "confidence": "EXTRACTED", "source_file": "src/analysis/topological.rs", "source_location": "L3", "weight": 1.0, "context": "import"}, {"source": "a_albdo_v_0_1_0_src_analysis_topological_rs", "target": "analysis_topological_topologicalsorter", "relation": "contains", "confidence": "EXTRACTED", "source_file": "src/analysis/topological.rs", "source_location": "L4", "weight": 1.0}, {"source": "analysis_topological_topologicalsorter", "target": "componentgraph", "relation": "references", "confidence": "EXTRACTED", "source_file": "src/analysis/topological.rs", "source_location": "L5", "weight": 1.0, "context": "field"}, {"source": "analysis_topological_topologicalsorter_a", "target": "analysis_topological_topologicalsorter_a_new", "relation": "method", "confidence": "EXTRACTED", "source_file": "src/analysis/topological.rs", "source_location": "L9", "weight": 1.0}, {"source": "analysis_topological_topologicalsorter_a_new", "target": "componentgraph", "relation": "references", "confidence": "EXTRACTED", "source_file": "src/analysis/topological.rs", "source_location": "L9", "weight": 1.0, "context": "parameter_type"}, {"source": "analysis_topological_topologicalsorter_a_new", "target": "self", "relation": "references", "confidence": "EXTRACTED", "source_file": "src/analysis/topological.rs", "source_location": "L9", "weight": 1.0, "context": "return_type"}, {"source": "analysis_topological_topologicalsorter_a", "target": "analysis_topological_topologicalsorter_a_sort", "relation": "method", "confidence": "EXTRACTED", "source_file": "src/analysis/topological.rs", "source_location": "L12", "weight": 1.0}, {"source": "analysis_topological_topologicalsorter_a_sort", "target": "result", "relation": "references", "confidence": "EXTRACTED", "source_file": "src/analysis/topological.rs", "source_location": "L12", "weight": 1.0, "context": "return_type"}, {"source": "analysis_topological_topologicalsorter_a_sort", "target": "vec", "relation": "references", "confidence": "EXTRACTED", "source_file": "src/analysis/topological.rs", "source_location": "L12", "weight": 1.0, "context": "generic_arg"}, {"source": "analysis_topological_topologicalsorter_a_sort", "target": "vec", "relation": "references", "confidence": "EXTRACTED", "source_file": "src/analysis/topological.rs", "source_location": "L12", "weight": 1.0, "context": "generic_arg"}, {"source": "analysis_topological_topologicalsorter_a_sort", "target": "componentid", "relation": "references", "confidence": "EXTRACTED", "source_file": "src/analysis/topological.rs", "source_location": "L12", "weight": 1.0, "context": "generic_arg"}, {"source": "analysis_topological_topologicalsorter_a", "target": "analysis_topological_topologicalsorter_a_sort_with_priority", "relation": "method", "confidence": "EXTRACTED", "source_file": "src/analysis/topological.rs", "source_location": "L68", "weight": 1.0}, {"source": "analysis_topological_topologicalsorter_a_sort_with_priority", "target": "hashmap", "relation": "references", "confidence": "EXTRACTED", "source_file": "src/analysis/topological.rs", "source_location": "L68", "weight": 1.0, "context": "parameter_type"}, {"source": "analysis_topological_topologicalsorter_a_sort_with_priority", "target": "componentid", "relation": "references", "confidence": "EXTRACTED", "source_file": "src/analysis/topological.rs", "source_location": "L68", "weight": 1.0, "context": "generic_arg"}, {"source": "analysis_topological_topologicalsorter_a_sort_with_priority", "target": "componentanalysis", "relation": "references", "confidence": "EXTRACTED", "source_file": "src/analysis/topological.rs", "source_location": "L68", "weight": 1.0, "context": "generic_arg"}, {"source": "analysis_topological_topologicalsorter_a_sort_with_priority", "target": "result", "relation": "references", "confidence": "EXTRACTED", "source_file": "src/analysis/topological.rs", "source_location": "L68", "weight": 1.0, "context": "return_type"}, {"source": "analysis_topological_topologicalsorter_a_sort_with_priority", "target": "vec", "relation": "references", "confidence": "EXTRACTED", "source_file": "src/analysis/topological.rs", "source_location": "L68", "weight": 1.0, "context": "generic_arg"}, {"source": "analysis_topological_topologicalsorter_a_sort_with_priority", "target": "vec", "relation": "references", "confidence": "EXTRACTED", "source_file": "src/analysis/topological.rs", "source_location": "L68", "weight": 1.0, "context": "generic_arg"}, {"source": "analysis_topological_topologicalsorter_a_sort_with_priority", "target": "componentid", "relation": "references", "confidence": "EXTRACTED", "source_file": "src/analysis/topological.rs", "source_location": "L68", "weight": 1.0, "context": "generic_arg"}, {"source": "analysis_topological_topologicalsorter_a", "target": "analysis_topological_topologicalsorter_a_create_batches", "relation": "method", "confidence": "EXTRACTED", "source_file": "src/analysis/topological.rs", "source_location": "L85", "weight": 1.0}, {"source": "analysis_topological_topologicalsorter_a_create_batches", "target": "vec", "relation": "references", "confidence": "EXTRACTED", "source_file": "src/analysis/topological.rs", "source_location": "L85", "weight": 1.0, "context": "parameter_type"}, {"source": "analysis_topological_topologicalsorter_a_create_batches", "target": "vec", "relation": "references", "confidence": "EXTRACTED", "source_file": "src/analysis/topological.rs", "source_location": "L85", "weight": 1.0, "context": "generic_arg"}, {"source": "analysis_topological_topologicalsorter_a_create_batches", "target": "componentid", "relation": "references", "confidence": "EXTRACTED", "source_file": "src/analysis/topological.rs", "source_location": "L85", "weight": 1.0, "context": "generic_arg"}, {"source": "analysis_topological_topologicalsorter_a_create_batches", "target": "hashmap", "relation": "references", "confidence": "EXTRACTED", "source_file": "src/analysis/topological.rs", "source_location": "L85", "weight": 1.0, "context": "parameter_type"}, {"source": "analysis_topological_topologicalsorter_a_create_batches", "target": "componentid", "relation": "references", "confidence": "EXTRACTED", "source_file": "src/analysis/topological.rs", "source_location": "L85", "weight": 1.0, "context": "generic_arg"}, {"source": "analysis_topological_topologicalsorter_a_create_batches", "target": "componentanalysis", "relation": "references", "confidence": "EXTRACTED", "source_file": "src/analysis/topological.rs", "source_location": "L85", "weight": 1.0, "context": "generic_arg"}, {"source": "analysis_topological_topologicalsorter_a_create_batches", "target": "vec", "relation": "references", "confidence": "EXTRACTED", "source_file": "src/analysis/topological.rs", "source_location": "L85", "weight": 1.0, "context": "return_type"}, {"source": "analysis_topological_topologicalsorter_a_create_batches", "target": "renderbatch", "relation": "references", "confidence": "EXTRACTED", "source_file": "src/analysis/topological.rs", "source_location": "L85", "weight": 1.0, "context": "generic_arg"}, {"source": "a_albdo_v_0_1_0_src_analysis_topological_rs", "target": "analysis_topological_find_critical_path", "relation": "contains", "confidence": "EXTRACTED", "source_file": "src/analysis/topological.rs", "source_location": "L112", "weight": 1.0}, {"source": "analysis_topological_find_critical_path", "target": "componentgraph", "relation": "references", "confidence": "EXTRACTED", "source_file": "src/analysis/topological.rs", "source_location": "L112", "weight": 1.0, "context": "parameter_type"}, {"source": "analysis_topological_find_critical_path", "target": "hashmap", "relation": "references", "confidence": "EXTRACTED", "source_file": "src/analysis/topological.rs", "source_location": "L112", "weight": 1.0, "context": "parameter_type"}, {"source": "analysis_topological_find_critical_path", "target": "componentid", "relation": "references", "confidence": "EXTRACTED", "source_file": "src/analysis/topological.rs", "source_location": "L112", "weight": 1.0, "context": "generic_arg"}, {"source": "analysis_topological_find_critical_path", "target": "componentanalysis", "relation": "references", "confidence": "EXTRACTED", "source_file": "src/analysis/topological.rs", "source_location": "L112", "weight": 1.0, "context": "generic_arg"}, {"source": "analysis_topological_find_critical_path", "target": "vec", "relation": "references", "confidence": "EXTRACTED", "source_file": "src/analysis/topological.rs", "source_location": "L112", "weight": 1.0, "context": "return_type"}, {"source": "analysis_topological_find_critical_path", "target": "componentid", "relation": "references", "confidence": "EXTRACTED", "source_file": "src/analysis/topological.rs", "source_location": "L112", "weight": 1.0, "context": "generic_arg"}, {"source": "a_albdo_v_0_1_0_src_analysis_topological_rs", "target": "analysis_topological_find_longest_path_from", "relation": "contains", "confidence": "EXTRACTED", "source_file": "src/analysis/topological.rs", "source_location": "L135", "weight": 1.0}, {"source": "analysis_topological_find_longest_path_from", "target": "componentid", "relation": "references", "confidence": "EXTRACTED", "source_file": "src/analysis/topological.rs", "source_location": "L135", "weight": 1.0, "context": "parameter_type"}, {"source": "analysis_topological_find_longest_path_from", "target": "componentgraph", "relation": "references", "confidence": "EXTRACTED", "source_file": "src/analysis/topological.rs", "source_location": "L135", "weight": 1.0, "context": "parameter_type"}, {"source": "analysis_topological_find_longest_path_from", "target": "hashmap", "relation": "references", "confidence": "EXTRACTED", "source_file": "src/analysis/topological.rs", "source_location": "L135", "weight": 1.0, "context": "parameter_type"}, {"source": "analysis_topological_find_longest_path_from", "target": "componentid", "relation": "references", "confidence": "EXTRACTED", "source_file": "src/analysis/topological.rs", "source_location": "L135", "weight": 1.0, "context": "generic_arg"}, {"source": "analysis_topological_find_longest_path_from", "target": "componentanalysis", "relation": "references", "confidence": "EXTRACTED", "source_file": "src/analysis/topological.rs", "source_location": "L135", "weight": 1.0, "context": "generic_arg"}, {"source": "analysis_topological_find_longest_path_from", "target": "hashset", "relation": "references", "confidence": "EXTRACTED", "source_file": "src/analysis/topological.rs", "source_location": "L135", "weight": 1.0, "context": "parameter_type"}, {"source": "analysis_topological_find_longest_path_from", "target": "componentid", "relation": "references", "confidence": "EXTRACTED", "source_file": "src/analysis/topological.rs", "source_location": "L135", "weight": 1.0, "context": "generic_arg"}, {"source": "analysis_topological_find_longest_path_from", "target": "vec", "relation": "references", "confidence": "EXTRACTED", "source_file": "src/analysis/topological.rs", "source_location": "L135", "weight": 1.0, "context": "return_type"}, {"source": "analysis_topological_find_longest_path_from", "target": "componentid", "relation": "references", "confidence": "EXTRACTED", "source_file": "src/analysis/topological.rs", "source_location": "L135", "weight": 1.0, "context": "generic_arg"}, {"source": "a_albdo_v_0_1_0_src_analysis_topological_rs", "target": "super", "relation": "imports_from", "confidence": "EXTRACTED", "source_file": "src/analysis/topological.rs", "source_location": "L176", "weight": 1.0, "context": "import"}, {"source": "a_albdo_v_0_1_0_src_analysis_topological_rs", "target": "analysis_topological_create_test_graph", "relation": "contains", "confidence": "EXTRACTED", "source_file": "src/analysis/topological.rs", "source_location": "L178", "weight": 1.0}, {"source": "analysis_topological_create_test_graph", "target": "componentgraph", "relation": "references", "confidence": "EXTRACTED", "source_file": "src/analysis/topological.rs", "source_location": "L178", "weight": 1.0, "context": "return_type"}, {"source": "a_albdo_v_0_1_0_src_analysis_topological_rs", "target": "analysis_topological_test_topological_sort", "relation": "contains", "confidence": "EXTRACTED", "source_file": "src/analysis/topological.rs", "source_location": "L199", "weight": 1.0}, {"source": "a_albdo_v_0_1_0_src_analysis_topological_rs", "target": "analysis_topological_test_empty_graph", "relation": "contains", "confidence": "EXTRACTED", "source_file": "src/analysis/topological.rs", "source_location": "L211", "weight": 1.0}, {"source": "a_albdo_v_0_1_0_src_analysis_topological_rs", "target": "analysis_topological_test_critical_path", "relation": "contains", "confidence": "EXTRACTED", "source_file": "src/analysis/topological.rs", "source_location": "L220", "weight": 1.0}, {"source": "analysis_topological_topologicalsorter_a_sort", "target": "analysis_topological_topologicalsorter_a_new", "relation": "calls", "context": "call", "confidence": "EXTRACTED", "source_file": "src/analysis/topological.rs", "source_location": "L15", "weight": 1.0}, {"source": "analysis_topological_topologicalsorter_a_sort_with_priority", "target": "analysis_topological_topologicalsorter_a_sort", "relation": "calls", "context": "call", "confidence": "EXTRACTED", "source_file": "src/analysis/topological.rs", "source_location": "L72", "weight": 1.0}, {"source": "analysis_topological_find_critical_path", "target": "analysis_topological_topologicalsorter_a_new", "relation": "calls", "context": "call", "confidence": "EXTRACTED", "source_file": "src/analysis/topological.rs", "source_location": "L116", "weight": 1.0}, {"source": "analysis_topological_find_critical_path", "target": "analysis_topological_find_longest_path_from", "relation": "calls", "context": "call", "confidence": "EXTRACTED", "source_file": "src/analysis/topological.rs", "source_location": "L126", "weight": 1.0}, {"source": "analysis_topological_find_longest_path_from", "target": "analysis_topological_topologicalsorter_a_new", "relation": "calls", "context": "call", "confidence": "EXTRACTED", "source_file": "src/analysis/topological.rs", "source_location": "L158", "weight": 1.0}, {"source": "analysis_topological_create_test_graph", "target": "analysis_topological_topologicalsorter_a_new", "relation": "calls", "context": "call", "confidence": "EXTRACTED", "source_file": "src/analysis/topological.rs", "source_location": "L179", "weight": 1.0}, {"source": "analysis_topological_test_topological_sort", "target": "analysis_topological_create_test_graph", "relation": "calls", "context": "call", "confidence": "EXTRACTED", "source_file": "src/analysis/topological.rs", "source_location": "L200", "weight": 1.0}, {"source": "analysis_topological_test_topological_sort", "target": "analysis_topological_topologicalsorter_a_new", "relation": "calls", "context": "call", "confidence": "EXTRACTED", "source_file": "src/analysis/topological.rs", "source_location": "L201", "weight": 1.0}, {"source": "analysis_topological_test_topological_sort", "target": "analysis_topological_topologicalsorter_a_sort", "relation": "calls", "context": "call", "confidence": "EXTRACTED", "source_file": "src/analysis/topological.rs", "source_location": "L203", "weight": 1.0}, {"source": "analysis_topological_test_empty_graph", "target": "analysis_topological_topologicalsorter_a_new", "relation": "calls", "context": "call", "confidence": "EXTRACTED", "source_file": "src/analysis/topological.rs", "source_location": "L212", "weight": 1.0}, {"source": "analysis_topological_test_empty_graph", "target": "analysis_topological_topologicalsorter_a_sort", "relation": "calls", "context": "call", "confidence": "EXTRACTED", "source_file": "src/analysis/topological.rs", "source_location": "L215", "weight": 1.0}, {"source": "analysis_topological_test_critical_path", "target": "analysis_topological_create_test_graph", "relation": "calls", "context": "call", "confidence": "EXTRACTED", "source_file": "src/analysis/topological.rs", "source_location": "L221", "weight": 1.0}, {"source": "analysis_topological_test_critical_path", "target": "analysis_topological_topologicalsorter_a_new", "relation": "calls", "context": "call", "confidence": "EXTRACTED", "source_file": "src/analysis/topological.rs", "source_location": "L222", "weight": 1.0}, {"source": "analysis_topological_test_critical_path", "target": "analysis_topological_find_critical_path", "relation": "calls", "context": "call", "confidence": "EXTRACTED", "source_file": "src/analysis/topological.rs", "source_location": "L229", "weight": 1.0}], "raw_calls": [{"caller_nid": "analysis_topological_topologicalsorter_a_sort", "callee": "validate", "is_member_call": true, "source_file": "A:\\AlBDO-v-0.1.0\\src\\analysis\\topological.rs", "source_location": "L13"}, {"caller_nid": "analysis_topological_topologicalsorter_a_sort", "callee": "calculate_out_degrees", "is_member_call": true, "source_file": "A:\\AlBDO-v-0.1.0\\src\\analysis\\topological.rs", "source_location": "L14"}, {"caller_nid": "analysis_topological_topologicalsorter_a_sort", "callee": "get_dependents", "is_member_call": true, "source_file": "A:\\AlBDO-v-0.1.0\\src\\analysis\\topological.rs", "source_location": "L36"}, {"caller_nid": "analysis_topological_topologicalsorter_a_sort", "callee": "get_mut", "is_member_call": true, "source_file": "A:\\AlBDO-v-0.1.0\\src\\analysis\\topological.rs", "source_location": "L43"}, {"caller_nid": "analysis_topological_topologicalsorter_a_sort_with_priority", "callee": "sort_by", "is_member_call": true, "source_file": "A:\\AlBDO-v-0.1.0\\src\\analysis\\topological.rs", "source_location": "L76"}, {"caller_nid": "analysis_topological_topologicalsorter_a_sort_with_priority", "callee": "unwrap_or", "is_member_call": true, "source_file": "A:\\AlBDO-v-0.1.0\\src\\analysis\\topological.rs", "source_location": "L77"}, {"caller_nid": "analysis_topological_topologicalsorter_a_sort_with_priority", "callee": "unwrap_or", "is_member_call": true, "source_file": "A:\\AlBDO-v-0.1.0\\src\\analysis\\topological.rs", "source_location": "L78"}, {"caller_nid": "analysis_topological_topologicalsorter_a_sort_with_priority", "callee": "partial_cmp", "is_member_call": true, "source_file": "A:\\AlBDO-v-0.1.0\\src\\analysis\\topological.rs", "source_location": "L79"}, {"caller_nid": "analysis_topological_topologicalsorter_a_create_batches", "callee": "into_iter", "is_member_call": true, "source_file": "A:\\AlBDO-v-0.1.0\\src\\analysis\\topological.rs", "source_location": "L90"}, {"caller_nid": "analysis_topological_topologicalsorter_a_create_batches", "callee": "fold", "is_member_call": true, "source_file": "A:\\AlBDO-v-0.1.0\\src\\analysis\\topological.rs", "source_location": "L94"}, {"caller_nid": "analysis_topological_topologicalsorter_a_create_batches", "callee": "filter_map", "is_member_call": true, "source_file": "A:\\AlBDO-v-0.1.0\\src\\analysis\\topological.rs", "source_location": "L94"}, {"caller_nid": "analysis_topological_find_critical_path", "callee": "calculate_out_degrees", "is_member_call": true, "source_file": "A:\\AlBDO-v-0.1.0\\src\\analysis\\topological.rs", "source_location": "L118"}, {"caller_nid": "analysis_topological_find_longest_path_from", "callee": "unwrap_or", "is_member_call": true, "source_file": "A:\\AlBDO-v-0.1.0\\src\\analysis\\topological.rs", "source_location": "L147"}, {"caller_nid": "analysis_topological_find_longest_path_from", "callee": "get_dependents", "is_member_call": true, "source_file": "A:\\AlBDO-v-0.1.0\\src\\analysis\\topological.rs", "source_location": "L152"}, {"caller_nid": "analysis_topological_find_longest_path_from", "callee": "find_longest_path_from", "is_member_call": false, "source_file": "A:\\AlBDO-v-0.1.0\\src\\analysis\\topological.rs", "source_location": "L162"}, {"caller_nid": "analysis_topological_create_test_graph", "callee": "add_component", "is_member_call": true, "source_file": "A:\\AlBDO-v-0.1.0\\src\\analysis\\topological.rs", "source_location": "L185"}, {"caller_nid": "analysis_topological_create_test_graph", "callee": "add_component", "is_member_call": true, "source_file": "A:\\AlBDO-v-0.1.0\\src\\analysis\\topological.rs", "source_location": "L186"}, {"caller_nid": "analysis_topological_create_test_graph", "callee": "add_component", "is_member_call": true, "source_file": "A:\\AlBDO-v-0.1.0\\src\\analysis\\topological.rs", "source_location": "L187"}, {"caller_nid": "analysis_topological_create_test_graph", "callee": "add_component", "is_member_call": true, "source_file": "A:\\AlBDO-v-0.1.0\\src\\analysis\\topological.rs", "source_location": "L188"}, {"caller_nid": "analysis_topological_create_test_graph", "callee": "add_dependency", "is_member_call": true, "source_file": "A:\\AlBDO-v-0.1.0\\src\\analysis\\topological.rs", "source_location": "L190"}, {"caller_nid": "analysis_topological_create_test_graph", "callee": "add_dependency", "is_member_call": true, "source_file": "A:\\AlBDO-v-0.1.0\\src\\analysis\\topological.rs", "source_location": "L191"}, {"caller_nid": "analysis_topological_create_test_graph", "callee": "add_dependency", "is_member_call": true, "source_file": "A:\\AlBDO-v-0.1.0\\src\\analysis\\topological.rs", "source_location": "L192"}, {"caller_nid": "analysis_topological_create_test_graph", "callee": "add_dependency", "is_member_call": true, "source_file": "A:\\AlBDO-v-0.1.0\\src\\analysis\\topological.rs", "source_location": "L193"}, {"caller_nid": "analysis_topological_test_critical_path", "callee": "components", "is_member_call": true, "source_file": "A:\\AlBDO-v-0.1.0\\src\\analysis\\topological.rs", "source_location": "L223"}]}